{
  "interviewee_id": "INT_027",
  "personal_info": {
    "name": "Story",
    "age": 43,
    "age_range": "40-44",
    "gender": "non_binary",
    "race_ethnicity": [
      "white"
    ],
    "education_level": "master's degree",
    "employment_status": "self_employed",
    "occupation": "store manager",
    "industry": "retail",
    "income_range": "$75k-$100k",
    "location": {
      "city": "Boston",
      "state": "MA",
      "country": "US",
      "region": "northeast"
    }
  },
  "interviews": [
    {
      "interview_id": "IV_027_20241124",
      "date": "2024-11-24",
      "start_time": "2024-11-24T09:30:00Z",
      "end_time": "2024-11-24T10:01:00Z",
      "duration_minutes": 44,
      "interview_type": "product_feedback",
      "interviewer_id": "STAFF_08",
      "location": "remote",
      "recording_quality": "good",
      "transcript_confidence_score": 0.8151789236007888,
      "completion_status": "completed",
      "transcript_file": "transcript_IV_027_20241124.json",
      "compensation_amount": 50
    }
  ],
  "study_participation": {
    "recruitment_channel": "email_campaign",
    "total_interviews_completed": 1,
    "total_compensation": 50,
    "hourly_compensation_rate": 68.18
  }
}