{
  "interviewee_id": "INT_076",
  "personal_info": {
    "name": "Winter",
    "age": 39,
    "age_range": "35-39",
    "gender": "non_binary",
    "race_ethnicity": [
      "black",
      "white"
    ],
    "education_level": "doctorate",
    "employment_status": "self_employed",
    "occupation": "cashier",
    "industry": "retail",
    "income_range": "$50k-$75k",
    "location": {
      "city": "Denver",
      "state": "CO",
      "country": "US",
      "region": "west"
    }
  },
  "interviews": [
    {
      "interview_id": "IV_076_20240825",
      "date": "2024-08-25",
      "start_time": "2024-08-25T16:30:00Z",
      "end_time": "2024-08-25T12:10:00Z",
      "duration_minutes": 87,
      "interview_type": "product_feedback",
      "interviewer_id": "STAFF_18",
      "location": "in_person",
      "recording_quality": "excellent",
      "transcript_confidence_score": 0.7664400467830863,
      "completion_status": "completed",
      "transcript_file": "transcript_IV_076_20240825.json",
      "compensation_amount": 100
    },
    {
      "interview_id": "IV_076_20240227",
      "date": "2024-02-27",
      "start_time": "2024-02-27T10:00:00Z",
      "end_time": "2024-02-27T12:04:00Z",
      "duration_minutes": 65,
      "interview_type": "initial_screening",
      "interviewer_id": "STAFF_17",
      "location": "in_person",
      "recording_quality": "fair",
      "transcript_confidence_score": 0.9316332066937123,
      "completion_status": "completed",
      "transcript_file": "transcript_IV_076_20240227.json",
      "compensation_amount": 75
    },
    {
      "interview_id": "IV_076_20240908",
      "date": "2024-09-08",
      "start_time": "2024-09-08T12:45:00Z",
      "end_time": "2024-09-08T10:55:00Z",
      "duration_minutes": 68,
      "interview_type": "user_experience",
      "interviewer_id": "STAFF_10",
      "location": "remote",
      "recording_quality": "good",
      "transcript_confidence_score": 0.7537610651693898,
      "completion_status": "completed",
      "transcript_file": "transcript_IV_076_20240908.json",
      "compensation_amount": 25
    }
  ],
  "study_participation": {
    "recruitment_channel": "email_campaign",
    "total_interviews_completed": 3,
    "total_compensation": 200,
    "hourly_compensation_rate": 54.55
  }
}